akerbp/mlpet/__init__.py
akerbp/mlpet/dataloader.py
akerbp/mlpet/dataset.py
akerbp/mlpet/feature_engineering.py
akerbp/mlpet/imputers.py
akerbp/mlpet/petrophysical_features.py
akerbp/mlpet/plotting.py
akerbp/mlpet/plotting_helpers.py
akerbp/mlpet/plotting_variables.py
akerbp/mlpet/preprocessors.py
akerbp/mlpet/transformer.py
akerbp/mlpet/utilities.py
akerbp/mlpet/data/__init__.py
akerbp/mlpet/data/mappings.py
akerbp_mlpet-6.0.2.dist-info/METADATA
akerbp_mlpet-6.0.2.dist-info/WHEEL
akerbp_mlpet-6.0.2.dist-info/licenses/LICENSE
akerbp_mlpet-6.0.2.dist-info/RECORD
