Metadata-Version: 2.4
Name: akerbp-mlpet
Version: 6.0.2
Summary: Package to prepare well log data for ML projects.
Project-URL: Repository, https://github.com/AkerBP/expres-ml-mlpet
Project-URL: Tracker, https://github.com/AkerBP/expres-ml-mlpet/issues
Author-email: Yann Van Crombrugge <yann.van.crombrugge@akerbp.com>, Saghar Asadi <saghar.asadi@akerbp.com>, Flavia Dias Casagrande <flavia.dias.casagrande@akerbp.com>
Maintainer-email: Yann Van Crombrugge <yann.van.crombrugge@akerbp.com>, Peder Aursand <peder.aursand@akerbp.com>
License-Expression: Apache-2.0
License-File: LICENSE
Requires-Python: <4.0,>=3.9
Requires-Dist: importlib-metadata>=4.12
Requires-Dist: joblib
Requires-Dist: lasio
Requires-Dist: pandas<3
Requires-Dist: plotly
Requires-Dist: pyyaml>=5.4.1
Requires-Dist: scikit-learn
Requires-Dist: scipy
Requires-Dist: tqdm
